LICENSE
README.md
setup.py
xcltk/__init__.py
xcltk/config.py
xcltk/xcltk.py
xcltk.egg-info/PKG-INFO
xcltk.egg-info/SOURCES.txt
xcltk.egg-info/dependency_links.txt
xcltk.egg-info/entry_points.txt
xcltk.egg-info/requires.txt
xcltk.egg-info/top_level.txt
xcltk/baf/__init__.py
xcltk/baf/fixref.py
xcltk/baf/genotype.py
xcltk/baf/io.py
xcltk/baf/localphase.py
xcltk/baf/pipeline.py
xcltk/baf/refphase.py
xcltk/baf/rpc.py
xcltk/baf/fc/__init__.py
xcltk/baf/fc/config.py
xcltk/baf/fc/core.py
xcltk/baf/fc/gfeature.py
xcltk/baf/fc/main.py
xcltk/baf/fc/mcount.py
xcltk/baf/fc/phasing.py
xcltk/baf/fc/thread.py
xcltk/baf/fc/utils.py
xcltk/rdr/__init__.py
xcltk/rdr/io.py
xcltk/rdr/fc/__init__.py
xcltk/rdr/fc/config.py
xcltk/rdr/fc/core.py
xcltk/rdr/fc/main.py
xcltk/rdr/fc/mcount.py
xcltk/rdr/fc/thread.py
xcltk/rdr/fc/utils.py
xcltk/tools/__init__.py
xcltk/tools/convert.py
xcltk/utils/__init__.py
xcltk/utils/base.py
xcltk/utils/csp_io.py
xcltk/utils/grange.py
xcltk/utils/gregion.py
xcltk/utils/gtf.py
xcltk/utils/hmm.py
xcltk/utils/sam.py
xcltk/utils/vcf.py
xcltk/utils/xlog.py
xcltk/utils/zfile.py