Metadata-Version: 2.1
Name: xcltk
Version: 0.5.1
Summary: xcltk - Toolkit for XClone
Home-page: https://github.com/hxj5/xcltk
Author: Xianjie Huang
Author-email: xianjie5@connect.hku.hk
License: Apache-2.0
Keywords: xclone,toolkit
Platform: UNKNOWN
